sop_infra/__init__.py
sop_infra/models.py
sop_infra/urls.py
sop_infra/utils.py
sop_infra/validators.py
sop_infra/api/__init__.py
sop_infra/api/serializers.py
sop_infra/api/urls.py
sop_infra/api/views.py
sop_infra/api/__pycache__/__init__.cpython-312.pyc
sop_infra/api/__pycache__/serializers.cpython-312.pyc
sop_infra/api/__pycache__/urls.cpython-312.pyc
sop_infra/api/__pycache__/views.cpython-312.pyc
sop_infra/forms/classification.py
sop_infra/forms/meraki_sdwan.py
sop_infra/forms/sizing.py
sop_infra/forms/__pycache__/classification.cpython-312.pyc
sop_infra/forms/__pycache__/meraki_sdwan.cpython-312.pyc
sop_infra/forms/__pycache__/sizing.cpython-312.pyc
sop_infra/migrations/0001_initial.py
sop_infra/migrations/0002_infraclassification_industrial_and_more.py
sop_infra/migrations/0003_infrasizing.py
sop_infra/migrations/0004_alter_infrasizing_ad_cumul_user_and_more.py
sop_infra/migrations/0005_alter_infrasizing_ad_cumul_user_and_more.py
sop_infra/migrations/0006_alter_infrasizing_ad_cumul_user_and_more.py
sop_infra/migrations/0007_alter_infrasizing_ad_cumul_user_and_more.py
sop_infra/migrations/0008_inframerakisdwan.py
sop_infra/migrations/0009_inframerakisdwan_master_location_and_more.py
sop_infra/migrations/0010_inframerakisdwan_nha_target.py
sop_infra/migrations/0011_alter_infraclassification_industrial_and_more.py
sop_infra/migrations/0012_inframerakisdwan_hub_default_route_setting_and_more.py
sop_infra/migrations/0013_alter_infraclassification_industrial_and_more.py
sop_infra/migrations/0014_alter_infrasizing_ad_cumul_user_and_more.py
sop_infra/migrations/__init__.py
sop_infra/migrations/__pycache__/0001_initial.cpython-312.pyc
sop_infra/migrations/__pycache__/0002_infraclassification_industrial_and_more.cpython-312.pyc
sop_infra/migrations/__pycache__/0003_infrasizing.cpython-312.pyc
sop_infra/migrations/__pycache__/0004_alter_infrasizing_ad_cumul_user_and_more.cpython-312.pyc
sop_infra-1.0.5.dist-info/METADATA
sop_infra-1.0.5.dist-info/WHEEL
sop_infra-1.0.5.dist-info/top_level.txt
sop_infra-1.0.5.dist-info/RECORD
