Metadata-Version: 2.1
Name: sop-infra
Version: 1.0.5
Summary: Manage infrastructure informations of each site.
Author: Leorevoir
Author-email: leo.quinzler@epitech.eu
Classifier: Framework :: Django
Classifier: Programming Language :: Python :: 3
